synutils/__init__.py
synutils/main.py
synavate-0.0.2.dist-info/LICENSE
synavate-0.0.2.dist-info/METADATA
synavate-0.0.2.dist-info/WHEEL
synavate-0.0.2.dist-info/RECORD
