Metadata-Version: 2.1
Name: synavate
Version: 0.0.2
Summary: Synavate Utility Library
Home-page: https://github.com/snyata/synavate_utils
License: MIT
Author: Synavate Labs
Requires-Python: >=3.9.0,<4.0
Classifier: License :: OSI Approved :: MIT License
Classifier: Programming Language :: Python :: 3
Classifier: Programming Language :: Python :: 3.9
Classifier: Programming Language :: Python :: 3.10
Classifier: Programming Language :: Python :: 3.11
Classifier: Programming Language :: Python :: 3.12
Requires-Dist: black (>=24.4.2,<25.0.0)
Requires-Dist: chromadb (>=0.5.3,<0.6.0)
Requires-Dist: datetime (>=5.5,<6.0)
Requires-Dist: fastapi (>=0.111.1,<0.112.0)
Requires-Dist: flake8 (>=7.1.0,<8.0.0)
Requires-Dist: isort (>=5.13.2,<6.0.0)
Requires-Dist: jinja2 (>=3.1.4,<4.0.0)
Requires-Dist: openai (>=1.35.13,<2.0.0)
Requires-Dist: pyarrow (>=17.0.0,<18.0.0)
Requires-Dist: recommonmark (>=0.7.1,<0.8.0)
Requires-Dist: uvicorn (>=0.30.1,<0.31.0)
Project-URL: Repository, https://github.com/snyata/synavate_utils
